kmc3recipes/_version.py
kmc3recipes/cooking_BACKUP_116041.py
kmc3recipes/cooking_BASE_116041.py
kmc3recipes/cooking_LOCAL_116041.py
kmc3recipes/cooking_REMOTE_116041.py
xraydc/_version.py
xraydc/cooking.py
xraydc/signal.py
xraydc-0.0.0.dist-info/METADATA
xraydc-0.0.0.dist-info/WHEEL
xraydc-0.0.0.dist-info/top_level.txt
xraydc-0.0.0.dist-info/RECORD
