Metadata-Version: 2.4
Name: xraydc
Version: 0.0.0
Summary: X-Ray Diffraction Cooking -- nx5d data processing recipes
Author-email: Matthias Rössle <matthias.roessle@helmholtz-berlin.de>, Florin Boariu <florin.pt@rootshell.ro>
Project-URL: Source Code, https://gitlab.com/kmc3-xpp/xraydc/
Project-URL: Bug Tracker, https://gitlab.com/kmc3-xpp/xraydc/
Classifier: Programming Language :: Python :: 3
Classifier: License :: OSI Approved :: GNU General Public License v3 or later (GPLv3+)
Classifier: Operating System :: POSIX :: Linux
Classifier: Development Status :: 2 - Pre-Alpha
Classifier: Environment :: Console
Classifier: Intended Audience :: Science/Research
Classifier: Topic :: Scientific/Engineering
Requires-Python: >=3.8
Requires-Dist: nx5d
Requires-Dist: xarray
Requires-Dist: scipy
Requires-Dist: dask
Requires-Dist: xrayutilities
Provides-Extra: all
Requires-Dist: xraydc[doc,test]; extra == "all"
Provides-Extra: test
Requires-Dist: pytest; extra == "test"
Requires-Dist: pytest-cov; extra == "test"
Requires-Dist: tqdm; extra == "test"
Provides-Extra: doc
Requires-Dist: mkdocs; extra == "doc"
Requires-Dist: mkdocstrings[python]; extra == "doc"
